Workbook

Sheet Inputs
A1: Pierre LBO One — inputs
A4: Input path | B4: Value | C4: Definition
A5: case | B5: 1 | C5: Scenario selector: integer 1–4
A6: last_fiscal_year_end | B6: 46203 | C6: ISO date; successive fiscal ends use EDATE(previous,12)
A7: deal_date | B7: 46204 | C7: ISO closing date, strictly within the first fiscal period
A8: exit_period | B8: 1 | C8: Forecast period 1–8; first post-close period is 1
A9: opening_revenue | B9: 2048 | C9: Annual entry assumption, GBP thousands
A10: opening_working_capital | B10: 0 | C10: Entry working-capital balance, GBP thousands
A11: entry_multiple | B11: 2 | C11: Multiple of first annual forecast EBITDA
A12: exit_multiple | B12: 2 | C12: Multiple of exit-period annual EBITDA
A13: exit_fee_rate | B13: 0 | C13: Fraction of nonnegative exit enterprise value
A14: tax_rate | B14: 0 | C14: Fraction of positive cash EBITDA less cash interest
A15: ordinary_equity_fraction | B15: 0.5 | C15: Fraction of entry equity invested in ordinary shares
A16: management_ordinary_fraction | B16: 0.3 | C16: Management ownership of ordinary shares only
... A26: revolver.maturity_period | B26: 12 | C26: Fiscal period bucket; no draws at or after maturity
A30: Forecast period | B30: working_capital_ratio
A31: 1 | B31: 0.015625
A32: 2 | B32: 0.015625
A33: 3 | B33: 0.015625
A34: 4 | B34: 0.015625
A35: 5 | B35: 0.015625
A36: 6 | B36: 0.015625
A37: 7 | B37: 0.015625
A38: 8 | B38: 0.015625
A41: All monetary amounts are GBP thousands. Blue cells are inputs; black cells are formulas.
A42: Input schema: scalar paths above; working_capital_ratio[8]; scenarios[4] of four 8-element arrays.
A43: Scenarios columns: revenue_growth, gross_profit_margin, opex_margin, capex (positive expenditure).
A44: Opening cash and revolver are zero. Entry is funded only by the term loan and equity; no entry fees.
A45: Annual EBITDA values entry/exit. Cash EBITDA and capex are stubbed; working-capital changes are not.
A46: No D&A, tax losses/refunds or deduction of PIK/preferred accrual; tax is on positive cash EBITDA less cash interest.
A47: Interest uses opening debt and ACT/365. Fiscal dates preserve the input day with sequential EDATE(previous,12).
A48: Revolver is repaid before term-loan cash sweep. Maturity is a fiscal period bucket, not a legal anniversary.
A49: Financing stops before an infeasible row. Forecast remains planned; exit/return cells become blank (JSON null).
A50: Preferred belongs only to the sponsor. No interim dividends; zero investment or zero payout has no finite XIRR.
A51: Liquidity roundoff is 1E-12 times the largest current cash-flow/obligation/capacity operand; no absolute floor.
A52: At the preferred hurdle, residual <= 1E-12 of equity proceeds is roundoff: all proceeds go to preferred.
... A54: Recalculate and save in Microsoft Excel before extracting cached outputs. No external links, macros or data tables.

Sheet Scenarios
A1: Scenario profiles — annual operating assumptions
A4: Case | B4: Period | C4: revenue_growth | D4: gross_profit_margin | E4: opex_margin | F4: capex
A5: 1 | B5: 1 | C5: 0 | D5: 0.375 | E5: 0.125 | F5: 512
A6: 1 | B6: 2 | C6: 0 | D6: 0.375 | E6: 0.125 | F6: 512
A7: 1 | B7: 3 | C7: 0 | D7: 0.375 | E7: 0.125 | F7: 512
A8: 1 | B8: 4 | C8: 0 | D8: 0.375 | E8: 0.125 | F8: 512
A9: 1 | B9: 5 | C9: 0 | D9: 0.375 | E9: 0.125 | F9: 512
A10: 1 | B10: 6 | C10: 0 | D10: 0.375 | E10: 0.125 | F10: 512
A11: 1 | B11: 7 | C11: 0 | D11: 0.375 | E11: 0.125 | F11: 512
A12: 1 | B12: 8 | C12: 0 | D12: 0.375 | E12: 0.125 | F12: 512
A13: 2 | B13: 1 | C13: 0 | D13: 0.375 | E13: 0.125 | F13: 512
A14: 2 | B14: 2 | C14: 0 | D14: 0.375 | E14: 0.125 | F14: 512
A15: 2 | B15: 3 | C15: 0 | D15: 0.375 | E15: 0.125 | F15: 512
A16: 2 | B16: 4 | C16: 0 | D16: 0.375 | E16: 0.125 | F16: 512
... A36: 4 | B36: 8 | C36: 0 | D36: 0.375 | E36: 0.125 | F36: 512

Sheet Forecast
A1: Annual forecast and actual-day cash-flow timing
A4: Period | B4: Previous fiscal end | C4: Fiscal end / dates | D4: Cash-flow start | E4: operating_fractions | F4: interest_year_fractions | G4: Selected revenue growth | H4: Selected GP margin | I4: Selected opex margin | J4: Annual capex | K4: WC ratio | L4: revenue | M4: gross_profit | N4: opex | O4: ebitda | P4: ebitda_margin | Q4: working_capital | R4: change_working_capital | S4: cash_capex | T4: cash_ebitda
A5: 1 | B5: =Inputs!$B$6 | C5: =EDATE(B5,12) | D5: =MAX(B5,Inputs!$B$7) | E5: =(C5-D5)/(C5-B5) | F5: =(C5-D5)/365 | G5: =INDEX(Scenarios!$C$5:$C$36,(Inputs!$B$5-1)*8+A5) | H5: =INDEX(Scenarios!$D$5:$D$36,(Inputs!$B$5-1)*8+A5) | I5: =INDEX(Scenarios!$E$5:$E$36,(Inputs!$B$5-1)*8+A5) | J5: =INDEX(Scenarios!$F$5:$F$36,(Inputs!$B$5-1)*8+A5) | K5: =Inputs!B31 | L5: =Inputs!$B$9*(1+G5) | M5: =L5*H5 | N5: =L5*I5 | O5: =M5-N5 | P5: =H5-I5 | Q5: =L5*K5 | R5: =Q5-Inputs!$B$10 | S5: =J5*E5 | T5: =O5*E5
A6: 2 | B6: =C5 | C6: =EDATE(B6,12) | D6: =MAX(B6,Inputs!$B$7) | E6: =(C6-D6)/(C6-B6) | F6: =(C6-D6)/365 | G6: =INDEX(Scenarios!$C$5:$C$36,(Inputs!$B$5-1)*8+A6) | H6: =INDEX(Scenarios!$D$5:$D$36,(Inputs!$B$5-1)*8+A6) | I6: =INDEX(Scenarios!$E$5:$E$36,(Inputs!$B$5-1)*8+A6) | J6: =INDEX(Scenarios!$F$5:$F$36,(Inputs!$B$5-1)*8+A6) | K6: =Inputs!B32 | L6: =L5*(1+G6) | M6: =L6*H6 | N6: =L6*I6 | O6: =M6-N6 | P6: =H6-I6 | Q6: =L6*K6 | R6: =Q6-Q5 | S6: =J6*E6 | T6: =O6*E6
A7: 3 | B7: =C6 | C7: =EDATE(B7,12) | D7: =MAX(B7,Inputs!$B$7) | E7: =(C7-D7)/(C7-B7) | F7: =(C7-D7)/365 | G7: =INDEX(Scenarios!$C$5:$C$36,(Inputs!$B$5-1)*8+A7) | H7: =INDEX(Scenarios!$D$5:$D$36,(Inputs!$B$5-1)*8+A7) | I7: =INDEX(Scenarios!$E$5:$E$36,(Inputs!$B$5-1)*8+A7) | J7: =INDEX(Scenarios!$F$5:$F$36,(Inputs!$B$5-1)*8+A7) | K7: =Inputs!B33 | L7: =L6*(1+G7) | M7: =L7*H7 | N7: =L7*I7 | O7: =M7-N7 | P7: =H7-I7 | Q7: =L7*K7 | R7: =Q7-Q6 | S7: =J7*E7 | T7: =O7*E7
A8: 4 | B8: =C7 | C8: =EDATE(B8,12) | D8: =MAX(B8,Inputs!$B$7) | E8: =(C8-D8)/(C8-B8) | F8: =(C8-D8)/365 | G8: =INDEX(Scenarios!$C$5:$C$36,(Inputs!$B$5-1)*8+A8) | H8: =INDEX(Scenarios!$D$5:$D$36,(Inputs!$B$5-1)*8+A8) | I8: =INDEX(Scenarios!$E$5:$E$36,(Inputs!$B$5-1)*8+A8) | J8: =INDEX(Scenarios!$F$5:$F$36,(Inputs!$B$5-1)*8+A8) | K8: =Inputs!B34 | L8: =L7*(1+G8) | M8: =L8*H8 | N8: =L8*I8 | O8: =M8-N8 | P8: =H8-I8 | Q8: =L8*K8 | R8: =Q8-Q7 | S8: =J8*E8 | T8: =O8*E8
A9: 5 | B9: =C8 | C9: =EDATE(B9,12) | D9: =MAX(B9,Inputs!$B$7) | E9: =(C9-D9)/(C9-B9) | F9: =(C9-D9)/365 | G9: =INDEX(Scenarios!$C$5:$C$36,(Inputs!$B$5-1)*8+A9) | H9: =INDEX(Scenarios!$D$5:$D$36,(Inputs!$B$5-1)*8+A9) | I9: =INDEX(Scenarios!$E$5:$E$36,(Inputs!$B$5-1)*8+A9) | J9: =INDEX(Scenarios!$F$5:$F$36,(Inputs!$B$5-1)*8+A9) | K9: =Inputs!B35 | L9: =L8*(1+G9) | M9: =L9*H9 | N9: =L9*I9 | O9: =M9-N9 | P9: =H9-I9 | Q9: =L9*K9 | R9: =Q9-Q8 | S9: =J9*E9 | T9: =O9*E9
A10: 6 | B10: =C9 | C10: =EDATE(B10,12) | D10: =MAX(B10,Inputs!$B$7) | E10: =(C10-D10)/(C10-B10) | F10: =(C10-D10)/365 | G10: =INDEX(Scenarios!$C$5:$C$36,(Inputs!$B$5-1)*8+A10) | H10: =INDEX(Scenarios!$D$5:$D$36,(Inputs!$B$5-1)*8+A10) | I10: =INDEX(Scenarios!$E$5:$E$36,(Inputs!$B$5-1)*8+A10) | J10: =INDEX(Scenarios!$F$5:$F$36,(Inputs!$B$5-1)*8+A10) | K10: =Inputs!B36 | L10: =L9*(1+G10) | M10: =L10*H10 | N10: =L10*I10 | O10: =M10-N10 | P10: =H10-I10 | Q10: =L10*K10 | R10: =Q10-Q9 | S10: =J10*E10 | T10: =O10*E10
A11: 7 | B11: =C10 | C11: =EDATE(B11,12) | D11: =MAX(B11,Inputs!$B$7) | E11: =(C11-D11)/(C11-B11) | F11: =(C11-D11)/365 | G11: =INDEX(Scenarios!$C$5:$C$36,(Inputs!$B$5-1)*8+A11) | H11: =INDEX(Scenarios!$D$5:$D$36,(Inputs!$B$5-1)*8+A11) | I11: =INDEX(Scenarios!$E$5:$E$36,(Inputs!$B$5-1)*8+A11) | J11: =INDEX(Scenarios!$F$5:$F$36,(Inputs!$B$5-1)*8+A11) | K11: =Inputs!B37 | L11: =L10*(1+G11) | M11: =L11*H11 | N11: =L11*I11 | O11: =M11-N11 | P11: =H11-I11 | Q11: =L11*K11 | R11: =Q11-Q10 | S11: =J11*E11 | T11: =O11*E11
A12: 8 | B12: =C11 | C12: =EDATE(B12,12) | D12: =MAX(B12,Inputs!$B$7) | E12: =(C12-D12)/(C12-B12) | F12: =(C12-D12)/365 | G12: =INDEX(Scenarios!$C$5:$C$36,(Inputs!$B$5-1)*8+A12) | H12: =INDEX(Scenarios!$D$5:$D$36,(Inputs!$B$5-1)*8+A12) | I12: =INDEX(Scenarios!$E$5:$E$36,(Inputs!$B$5-1)*8+A12) | J12: =INDEX(Scenarios!$F$5:$F$36,(Inputs!$B$5-1)*8+A12) | K12: =Inputs!B38 | L12: =L11*(1+G12) | M12: =L12*H12 | N12: =L12*I12 | O12: =M12-N12 | P12: =H12-I12 | Q12: =L12*K12 | R12: =Q12-Q11 | S12: =J12*E12 | T12: =O12*E12

Sheet Debt
A1: Sequential debt, cash and liquidity waterfall
A2: Candidate obligations are diagnostic only on a failed row; executed flows and balances are blank.
A4: Period | B4: Evaluate row? | C4: Opening TLB | D4: Opening RCF | E4: Opening cash | F4: tlb_interest | G4: rcf_interest | H4: cash_interest | I4: tlb_pik | J4: cash_taxes | K4: pre_financing_cash_flow | L4: Proposed mandatory TLB repayment | M4: Proposed mandatory RCF repayment | N4: Cash before repayments | O4: Required draw | P4: Available draw | Q4: Potential funding shortfall | R4: Row status | S4: rcf_draw | T4: Cash after mandatory repayments | U4: Interim RCF | V4: Voluntary RCF repayment | W4: rcf_repayment (total) | X4: Cash after RCF repayment | Y4: tlb_sweep | Z4: tlb_balance | AA4: rcf_balance | AB4: cash_balance
A5: 1 | B5: =AND(A5<=Inputs!$B$8,TRUE) | C5: =IF(B5,Inputs!$B$18,"") | D5: =IF(B5,0,"") | E5: =IF(B5,0,"") | F5: =IF(B5,C5*Inputs!$B$19*Forecast!F5,"") | G5: =IF(B5,D5*Inputs!$B$25*Forecast!F5,"") | H5: =IF(B5,F5+G5,"") | I5: =IF(B5,C5*Inputs!$B$20*Forecast!F5,"") | J5: =IF(B5,MAX(Forecast!T5-H5,0)*Inputs!$B$14,"") | K5: =IF(B5,Forecast!T5-Forecast!S5-Forecast!R5-J5,"") | L5: =IF(B5,IF(A5>=Inputs!$B$23,C5+I5,MIN(C5+I5,Inputs!$B$18*Inputs!$B$21*Forecast!E5)),"") | M5: =IF(B5,IF(A5>=Inputs!$B$26,D5,0),"") | N5: =IF(B5,E5+K5-H5,"") | O5: =IF(B5,MAX(L5+M5-N5,0),"") | P5: =IF(B5,IF(A5<Inputs!$B$26,MAX(Inputs!$B$24-D5,0),0),"") | Q5: =IF(B5,MAX(O5-P5,0),"") | R5: =IF(B5,IF(Q5>1E-12*MAX(E5,ABS(Forecast!T5),Forecast!S5,ABS(Forecast!R5),J5,H5,L5+M5,P5),"liquidity_shortfall","ok"),"not_projected") | S5: =IF(R5="ok",MIN(O5,P5),"") | T5: =IF(R5="ok",MAX(N5+S5-L5-M5,0),"") | U5: =IF(R5="ok",D5+S5-M5,"") | V5: =IF(R5="ok",MIN(T5,U5),"") | W5: =IF(R5="ok",M5+V5,"") | X5: =IF(R5="ok",T5-V5,"") | Y5: =IF(R5="ok",MIN(X5*Inputs!$B$22,C5+I5-L5),"") | Z5: =IF(R5="ok",C5+I5-L5-Y5,"") | AA5: =IF(R5="ok",U5-V5,"") | AB5: =IF(R5="ok",X5-Y5,"")
A6: 2 | B6: =AND(A6<=Inputs!$B$8,R5="ok") | C6: =IF(B6,Z5,"") | D6: =IF(B6,AA5,"") | E6: =IF(B6,AB5,"") | F6: =IF(B6,C6*Inputs!$B$19*Forecast!F6,"") | G6: =IF(B6,D6*Inputs!$B$25*Forecast!F6,"") | H6: =IF(B6,F6+G6,"") | I6: =IF(B6,C6*Inputs!$B$20*Forecast!F6,"") | J6: =IF(B6,MAX(Forecast!T6-H6,0)*Inputs!$B$14,"") | K6: =IF(B6,Forecast!T6-Forecast!S6-Forecast!R6-J6,"") | L6: =IF(B6,IF(A6>=Inputs!$B$23,C6+I6,MIN(C6+I6,Inputs!$B$18*Inputs!$B$21*Forecast!E6)),"") | M6: =IF(B6,IF(A6>=Inputs!$B$26,D6,0),"") | N6: =IF(B6,E6+K6-H6,"") | O6: =IF(B6,MAX(L6+M6-N6,0),"") | P6: =IF(B6,IF(A6<Inputs!$B$26,MAX(Inputs!$B$24-D6,0),0),"") | Q6: =IF(B6,MAX(O6-P6,0),"") | R6: =IF(B6,IF(Q6>1E-12*MAX(E6,ABS(Forecast!T6),Forecast!S6,ABS(Forecast!R6),J6,H6,L6+M6,P6),"liquidity_shortfall","ok"),"not_projected") | S6: =IF(R6="ok",MIN(O6,P6),"") | T6: =IF(R6="ok",MAX(N6+S6-L6-M6,0),"") | U6: =IF(R6="ok",D6+S6-M6,"") | V6: =IF(R6="ok",MIN(T6,U6),"") | W6: =IF(R6="ok",M6+V6,"") | X6: =IF(R6="ok",T6-V6,"") | Y6: =IF(R6="ok",MIN(X6*Inputs!$B$22,C6+I6-L6),"") | Z6: =IF(R6="ok",C6+I6-L6-Y6,"") | AA6: =IF(R6="ok",U6-V6,"") | AB6: =IF(R6="ok",X6-Y6,"")
A7: 3 | B7: =AND(A7<=Inputs!$B$8,R6="ok") | C7: =IF(B7,Z6,"") | D7: =IF(B7,AA6,"") | E7: =IF(B7,AB6,"") | F7: =IF(B7,C7*Inputs!$B$19*Forecast!F7,"") | G7: =IF(B7,D7*Inputs!$B$25*Forecast!F7,"") | H7: =IF(B7,F7+G7,"") | I7: =IF(B7,C7*Inputs!$B$20*Forecast!F7,"") | J7: =IF(B7,MAX(Forecast!T7-H7,0)*Inputs!$B$14,"") | K7: =IF(B7,Forecast!T7-Forecast!S7-Forecast!R7-J7,"") | L7: =IF(B7,IF(A7>=Inputs!$B$23,C7+I7,MIN(C7+I7,Inputs!$B$18*Inputs!$B$21*Forecast!E7)),"") | M7: =IF(B7,IF(A7>=Inputs!$B$26,D7,0),"") | N7: =IF(B7,E7+K7-H7,"") | O7: =IF(B7,MAX(L7+M7-N7,0),"") | P7: =IF(B7,IF(A7<Inputs!$B$26,MAX(Inputs!$B$24-D7,0),0),"") | Q7: =IF(B7,MAX(O7-P7,0),"") | R7: =IF(B7,IF(Q7>1E-12*MAX(E7,ABS(Forecast!T7),Forecast!S7,ABS(Forecast!R7),J7,H7,L7+M7,P7),"liquidity_shortfall","ok"),"not_projected") | S7: =IF(R7="ok",MIN(O7,P7),"") | T7: =IF(R7="ok",MAX(N7+S7-L7-M7,0),"") | U7: =IF(R7="ok",D7+S7-M7,"") | V7: =IF(R7="ok",MIN(T7,U7),"") | W7: =IF(R7="ok",M7+V7,"") | X7: =IF(R7="ok",T7-V7,"") | Y7: =IF(R7="ok",MIN(X7*Inputs!$B$22,C7+I7-L7),"") | Z7: =IF(R7="ok",C7+I7-L7-Y7,"") | AA7: =IF(R7="ok",U7-V7,"") | AB7: =IF(R7="ok",X7-Y7,"")
A8: 4 | B8: =AND(A8<=Inputs!$B$8,R7="ok") | C8: =IF(B8,Z7,"") | D8: =IF(B8,AA7,"") | E8: =IF(B8,AB7,"") | F8: =IF(B8,C8*Inputs!$B$19*Forecast!F8,"") | G8: =IF(B8,D8*Inputs!$B$25*Forecast!F8,"") | H8: =IF(B8,F8+G8,"") | I8: =IF(B8,C8*Inputs!$B$20*Forecast!F8,"") | J8: =IF(B8,MAX(Forecast!T8-H8,0)*Inputs!$B$14,"") | K8: =IF(B8,Forecast!T8-Forecast!S8-Forecast!R8-J8,"") | L8: =IF(B8,IF(A8>=Inputs!$B$23,C8+I8,MIN(C8+I8,Inputs!$B$18*Inputs!$B$21*Forecast!E8)),"") | M8: =IF(B8,IF(A8>=Inputs!$B$26,D8,0),"") | N8: =IF(B8,E8+K8-H8,"") | O8: =IF(B8,MAX(L8+M8-N8,0),"") | P8: =IF(B8,IF(A8<Inputs!$B$26,MAX(Inputs!$B$24-D8,0),0),"") | Q8: =IF(B8,MAX(O8-P8,0),"") | R8: =IF(B8,IF(Q8>1E-12*MAX(E8,ABS(Forecast!T8),Forecast!S8,ABS(Forecast!R8),J8,H8,L8+M8,P8),"liquidity_shortfall","ok"),"not_projected") | S8: =IF(R8="ok",MIN(O8,P8),"") | T8: =IF(R8="ok",MAX(N8+S8-L8-M8,0),"") | U8: =IF(R8="ok",D8+S8-M8,"") | V8: =IF(R8="ok",MIN(T8,U8),"") | W8: =IF(R8="ok",M8+V8,"") | X8: =IF(R8="ok",T8-V8,"") | Y8: =IF(R8="ok",MIN(X8*Inputs!$B$22,C8+I8-L8),"") | Z8: =IF(R8="ok",C8+I8-L8-Y8,"") | AA8: =IF(R8="ok",U8-V8,"") | AB8: =IF(R8="ok",X8-Y8,"")
A9: 5 | B9: =AND(A9<=Inputs!$B$8,R8="ok") | C9: =IF(B9,Z8,"") | D9: =IF(B9,AA8,"") | E9: =IF(B9,AB8,"") | F9: =IF(B9,C9*Inputs!$B$19*Forecast!F9,"") | G9: =IF(B9,D9*Inputs!$B$25*Forecast!F9,"") | H9: =IF(B9,F9+G9,"") | I9: =IF(B9,C9*Inputs!$B$20*Forecast!F9,"") | J9: =IF(B9,MAX(Forecast!T9-H9,0)*Inputs!$B$14,"") | K9: =IF(B9,Forecast!T9-Forecast!S9-Forecast!R9-J9,"") | L9: =IF(B9,IF(A9>=Inputs!$B$23,C9+I9,MIN(C9+I9,Inputs!$B$18*Inputs!$B$21*Forecast!E9)),"") | M9: =IF(B9,IF(A9>=Inputs!$B$26,D9,0),"") | N9: =IF(B9,E9+K9-H9,"") | O9: =IF(B9,MAX(L9+M9-N9,0),"") | P9: =IF(B9,IF(A9<Inputs!$B$26,MAX(Inputs!$B$24-D9,0),0),"") | Q9: =IF(B9,MAX(O9-P9,0),"") | R9: =IF(B9,IF(Q9>1E-12*MAX(E9,ABS(Forecast!T9),Forecast!S9,ABS(Forecast!R9),J9,H9,L9+M9,P9),"liquidity_shortfall","ok"),"not_projected") | S9: =IF(R9="ok",MIN(O9,P9),"") | T9: =IF(R9="ok",MAX(N9+S9-L9-M9,0),"") | U9: =IF(R9="ok",D9+S9-M9,"") | V9: =IF(R9="ok",MIN(T9,U9),"") | W9: =IF(R9="ok",M9+V9,"") | X9: =IF(R9="ok",T9-V9,"") | Y9: =IF(R9="ok",MIN(X9*Inputs!$B$22,C9+I9-L9),"") | Z9: =IF(R9="ok",C9+I9-L9-Y9,"") | AA9: =IF(R9="ok",U9-V9,"") | AB9: =IF(R9="ok",X9-Y9,"")
A10: 6 | B10: =AND(A10<=Inputs!$B$8,R9="ok") | C10: =IF(B10,Z9,"") | D10: =IF(B10,AA9,"") | E10: =IF(B10,AB9,"") | F10: =IF(B10,C10*Inputs!$B$19*Forecast!F10,"") | G10: =IF(B10,D10*Inputs!$B$25*Forecast!F10,"") | H10: =IF(B10,F10+G10,"") | I10: =IF(B10,C10*Inputs!$B$20*Forecast!F10,"") | J10: =IF(B10,MAX(Forecast!T10-H10,0)*Inputs!$B$14,"") | K10: =IF(B10,Forecast!T10-Forecast!S10-Forecast!R10-J10,"") | L10: =IF(B10,IF(A10>=Inputs!$B$23,C10+I10,MIN(C10+I10,Inputs!$B$18*Inputs!$B$21*Forecast!E10)),"") | M10: =IF(B10,IF(A10>=Inputs!$B$26,D10,0),"") | N10: =IF(B10,E10+K10-H10,"") | O10: =IF(B10,MAX(L10+M10-N10,0),"") | P10: =IF(B10,IF(A10<Inputs!$B$26,MAX(Inputs!$B$24-D10,0),0),"") | Q10: =IF(B10,MAX(O10-P10,0),"") | R10: =IF(B10,IF(Q10>1E-12*MAX(E10,ABS(Forecast!T10),Forecast!S10,ABS(Forecast!R10),J10,H10,L10+M10,P10),"liquidity_shortfall","ok"),"not_projected") | S10: =IF(R10="ok",MIN(O10,P10),"") | T10: =IF(R10="ok",MAX(N10+S10-L10-M10,0),"") | U10: =IF(R10="ok",D10+S10-M10,"") | V10: =IF(R10="ok",MIN(T10,U10),"") | W10: =IF(R10="ok",M10+V10,"") | X10: =IF(R10="ok",T10-V10,"") | Y10: =IF(R10="ok",MIN(X10*Inputs!$B$22,C10+I10-L10),"") | Z10: =IF(R10="ok",C10+I10-L10-Y10,"") | AA10: =IF(R10="ok",U10-V10,"") | AB10: =IF(R10="ok",X10-Y10,"")
A11: 7 | B11: =AND(A11<=Inputs!$B$8,R10="ok") | C11: =IF(B11,Z10,"") | D11: =IF(B11,AA10,"") | E11: =IF(B11,AB10,"") | F11: =IF(B11,C11*Inputs!$B$19*Forecast!F11,"") | G11: =IF(B11,D11*Inputs!$B$25*Forecast!F11,"") | H11: =IF(B11,F11+G11,"") | I11: =IF(B11,C11*Inputs!$B$20*Forecast!F11,"") | J11: =IF(B11,MAX(Forecast!T11-H11,0)*Inputs!$B$14,"") | K11: =IF(B11,Forecast!T11-Forecast!S11-Forecast!R11-J11,"") | L11: =IF(B11,IF(A11>=Inputs!$B$23,C11+I11,MIN(C11+I11,Inputs!$B$18*Inputs!$B$21*Forecast!E11)),"") | M11: =IF(B11,IF(A11>=Inputs!$B$26,D11,0),"") | N11: =IF(B11,E11+K11-H11,"") | O11: =IF(B11,MAX(L11+M11-N11,0),"") | P11: =IF(B11,IF(A11<Inputs!$B$26,MAX(Inputs!$B$24-D11,0),0),"") | Q11: =IF(B11,MAX(O11-P11,0),"") | R11: =IF(B11,IF(Q11>1E-12*MAX(E11,ABS(Forecast!T11),Forecast!S11,ABS(Forecast!R11),J11,H11,L11+M11,P11),"liquidity_shortfall","ok"),"not_projected") | S11: =IF(R11="ok",MIN(O11,P11),"") | T11: =IF(R11="ok",MAX(N11+S11-L11-M11,0),"") | U11: =IF(R11="ok",D11+S11-M11,"") | V11: =IF(R11="ok",MIN(T11,U11),"") | W11: =IF(R11="ok",M11+V11,"") | X11: =IF(R11="ok",T11-V11,"") | Y11: =IF(R11="ok",MIN(X11*Inputs!$B$22,C11+I11-L11),"") | Z11: =IF(R11="ok",C11+I11-L11-Y11,"") | AA11: =IF(R11="ok",U11-V11,"") | AB11: =IF(R11="ok",X11-Y11,"")
A12: 8 | B12: =AND(A12<=Inputs!$B$8,R11="ok") | C12: =IF(B12,Z11,"") | D12: =IF(B12,AA11,"") | E12: =IF(B12,AB11,"") | F12: =IF(B12,C12*Inputs!$B$19*Forecast!F12,"") | G12: =IF(B12,D12*Inputs!$B$25*Forecast!F12,"") | H12: =IF(B12,F12+G12,"") | I12: =IF(B12,C12*Inputs!$B$20*Forecast!F12,"") | J12: =IF(B12,MAX(Forecast!T12-H12,0)*Inputs!$B$14,"") | K12: =IF(B12,Forecast!T12-Forecast!S12-Forecast!R12-J12,"") | L12: =IF(B12,IF(A12>=Inputs!$B$23,C12+I12,MIN(C12+I12,Inputs!$B$18*Inputs!$B$21*Forecast!E12)),"") | M12: =IF(B12,IF(A12>=Inputs!$B$26,D12,0),"") | N12: =IF(B12,E12+K12-H12,"") | O12: =IF(B12,MAX(L12+M12-N12,0),"") | P12: =IF(B12,IF(A12<Inputs!$B$26,MAX(Inputs!$B$24-D12,0),0),"") | Q12: =IF(B12,MAX(O12-P12,0),"") | R12: =IF(B12,IF(Q12>1E-12*MAX(E12,ABS(Forecast!T12),Forecast!S12,ABS(Forecast!R12),J12,H12,L12+M12,P12),"liquidity_shortfall","ok"),"not_projected") | S12: =IF(R12="ok",MIN(O12,P12),"") | T12: =IF(R12="ok",MAX(N12+S12-L12-M12,0),"") | U12: =IF(R12="ok",D12+S12-M12,"") | V12: =IF(R12="ok",MIN(T12,U12),"") | W12: =IF(R12="ok",M12+V12,"") | X12: =IF(R12="ok",T12-V12,"") | Y12: =IF(R12="ok",MIN(X12*Inputs!$B$22,C12+I12-L12),"") | Z12: =IF(R12="ok",C12+I12-L12-Y12,"") | AA12: =IF(R12="ok",U12-V12,"") | AB12: =IF(R12="ok",X12-Y12,"")

Sheet Returns
A1: Entry funding, exit priority waterfall and native XIRR
A4: Output | B4: Value
A5: entry_ebitda | B5: =Forecast!O5
A6: entry_ev | B6: =B5*Inputs!$B$11
A7: entry_equity | B7: =B6-Inputs!$B$18
A8: ordinary_equity | B8: =B7*Inputs!$B$15
A9: preferred_equity | B9: =B7-B8
A10: sponsor_investment | B10: =B7-B11
A11: management_investment | B11: =B8*Inputs!$B$16
A13: exit_date | B13: =INDEX(Forecast!C5:C12,Inputs!$B$8)
A14: holding_period_years | B14: =(B13-Inputs!$B$7)/365
A16: status | B16: =IF(COUNTIF(Debt!R5:R12,"liquidity_shortfall")>0,"liquidity_shortfall","ok")
A17: failure_period | B17: =IF(B16="ok","",MATCH("liquidity_shortfall",Debt!R5:R12,0))
A18: funding_shortfall | B18: =IF(B16="ok",0,INDEX(Debt!Q5:Q12,B17))
A20: exit_ev | B20: =IF($B$16="ok",INDEX(Forecast!O5:O12,Inputs!$B$8)*Inputs!$B$12,"")
A21: exit_fees | B21: =IF($B$16="ok",MAX(B20,0)*Inputs!$B$13,"")
A22: exit_debt | B22: =IF($B$16="ok",INDEX(Debt!Z5:Z12,Inputs!$B$8)+INDEX(Debt!AA5:AA12,Inputs!$B$8),"")
A23: exit_cash | B23: =IF($B$16="ok",INDEX(Debt!AB5:AB12,Inputs!$B$8),"")
A24: equity_value_before_floor | B24: =IF($B$16="ok",B20-B21-B22+B23,"")
A25: equity_proceeds | B25: =IF($B$16="ok",MAX(B24,0),"")
A27: preferred_accrued | B27: =IF($B$16="ok",B9*(1+Inputs!$B$17)^B14,"")
A28: preferred_payout | B28: =IF($B$16="ok",IF(B25-B27<=1E-12*B25,B25,B27),"")
A29: ordinary_payout | B29: =IF($B$16="ok",B25-B28,"")
A30: sponsor_proceeds | B30: =IF($B$16="ok",B28+B29*(1-Inputs!$B$16),"")
A31: management_proceeds | B31: =IF($B$16="ok",B29*Inputs!$B$16,"")
A33: deal_mom | B33: =IF(AND($B$16="ok",B7>0),B25/B7,"")
A34: sponsor_mom | B34: =IF(AND($B$16="ok",B10>0),B30/B10,"")
A35: management_mom | B35: =IF(AND($B$16="ok",B11>0),B31/B11,"")
A37: deal_irr | B37: =IF(AND($B$16="ok",B7>0,B25>0),XIRR(C44:C45,$B$44:$B$45,MAX(-0.999999999999999,EXP(LN(B25/B7)/$B$14)-1)),"")
A38: sponsor_irr | B38: =IF(AND($B$16="ok",B10>0,B30>0),XIRR(D44:D45,$B$44:$B$45,MAX(-0.999999999999999,EXP(LN(B30/B10)/$B$14)-1)),"")
A39: management_irr | B39: =IF(AND($B$16="ok",B11>0,B31>0),XIRR(E44:E45,$B$44:$B$45,MAX(-0.999999999999999,EXP(LN(B31/B11)/$B$14)-1)),"")
A43: Cash-flow event | B43: Actual date | C43: Deal | D43: Sponsor | E43: Management
A44: Entry investment | B44: =Inputs!$B$7 | C44: =-B7 | D44: =-B10 | E44: =-B11
A45: Exit distribution | B45: =B13 | C45: =IF($B$16="ok",B25,"") | D45: =IF($B$16="ok",B30,"") | E45: =IF($B$16="ok",B31,"")
A48: Blank valuation or return cells map to JSON null, never fabricated zero returns.
A49: Priority: sponsor preferred first, then ordinary split; distributions sum to equity proceeds.
