Workbook

Sheet Inputs
A1: Pierre LBO One — inputs
A4: Input path | B4: Value | C4: Definition
A5: case | B5: 1 | C5: Scenario selector: integer 1–4
A6: last_fiscal_year_end | B6: 44531 | C6: ISO date; successive fiscal ends use EDATE(previous,12)
A7: deal_date | B7: 44593 | C7: ISO closing date, strictly within the first fiscal period
A8: exit_period | B8: 5 | C8: Forecast period 1–8; first post-close period is 1
A9: opening_revenue | B9: 171697 | C9: Annual entry assumption, GBP thousands
A10: opening_working_capital | B10: 6653 | C10: Entry working-capital balance, GBP thousands
A11: entry_multiple | B11: 8 | C11: Multiple of first annual forecast EBITDA
A12: exit_multiple | B12: 8 | C12: Multiple of exit-period annual EBITDA
A13: exit_fee_rate | B13: 0.03 | C13: Fraction of nonnegative exit enterprise value
A14: tax_rate | B14: 0.25 | C14: Fraction of positive cash EBITDA less cash interest
A15: ordinary_equity_fraction | B15: 0.1 | C15: Fraction of entry equity invested in ordinary shares
A16: management_ordinary_fraction | B16: 0.1 | C16: Management ownership of ordinary shares only
... A26: revolver.maturity_period | B26: 100 | C26: Fiscal period bucket; no draws at or after maturity
A30: Forecast period | B30: working_capital_ratio
A31: 1 | B31: 0.065928097
A32: 2 | B32: 0.066246987
A33: 3 | B33: 0.063049853
A34: 4 | B34: 0.060610341
A35: 5 | B35: 0.059048756
A36: 6 | B36: 0.059048756
A37: 7 | B37: 0.059048756
A38: 8 | B38: 0.059048756
A41: All monetary amounts are GBP thousands. Blue cells are inputs; black cells are formulas.
A42: Input schema: scalar paths above; working_capital_ratio[8]; scenarios[4] of four 8-element arrays.
A43: Scenarios columns: revenue_growth, gross_profit_margin, opex_margin, capex (positive expenditure).
A44: Opening cash and revolver are zero. Entry is funded only by the term loan and equity; no entry fees.
A45: Annual EBITDA values entry/exit. Cash EBITDA and capex are stubbed; working-capital changes are not.
A46: No D&A, tax losses/refunds or deduction of PIK/preferred accrual; tax is on positive cash EBITDA less cash interest.
A47: Interest uses opening debt and ACT/365. Fiscal dates preserve the input day with sequential EDATE(previous,12).
A48: Revolver is repaid before term-loan cash sweep. Maturity is a fiscal period bucket, not a legal anniversary.
A49: Financing stops before an infeasible row. Forecast remains planned; exit/return cells become blank (JSON null).
A50: Preferred belongs only to the sponsor. No interim dividends; zero investment or zero payout has no finite XIRR.
A51: At the preferred hurdle, residual <= 1E-12 of equity proceeds is roundoff: all proceeds go to preferred.
A52: XIRR uses actual dated cash flows; a log-ratio starting guess stabilizes convergence for extreme two-flow returns.
A53: Recalculate and save in Microsoft Excel before extracting cached outputs. No external links, macros or data tables.

Sheet Scenarios
A1: Scenario profiles — annual operating assumptions
A4: Case | B4: Period | C4: revenue_growth | D4: gross_profit_margin | E4: opex_margin | F4: capex
A5: 1 | B5: 1 | C5: -0.077887208 | D5: 0.13708598 | E5: 0.049910311 | F5: 48
A6: 1 | B6: 2 | C6: 0.22105303 | D6: 0.14846732 | E6: 0.048809758 | F6: 194
A7: 1 | B7: 3 | C7: 0.20650521 | D7: 0.15822486 | E7: 0.048292775 | F7: 234
A8: 1 | B8: 4 | C8: 0.18377322 | D8: 0.16634433 | E8: 0.047778406 | F8: 345
A9: 1 | B9: 5 | C9: 0.15874585 | D9: 0.17213281 | E9: 0.047518433 | F9: 400
A10: 1 | B10: 6 | C10: 0.13 | D10: 0.17513281 | E10: 0.047518433 | F10: 443
A11: 1 | B11: 7 | C11: 0.12 | D11: 0.17813281 | E11: 0.047518433 | F11: 486
A12: 1 | B12: 8 | C12: 0.11 | D12: 0.18113281 | E12: 0.047518433 | F12: 529
A13: 2 | B13: 1 | C13: -0.077887208 | D13: 0.13708598 | E13: 0.049910311 | F13: 48
A14: 2 | B14: 2 | C14: 0.21605303 | D14: 0.13846732 | E14: 0.053809758 | F14: 231
A15: 2 | B15: 3 | C15: 0.20150521 | D15: 0.14822486 | E15: 0.053292775 | F15: 271
A16: 2 | B16: 4 | C16: 0.17877322 | D16: 0.15634433 | E16: 0.052778406 | F16: 382
... A36: 4 | B36: 8 | C36: 0.095 | D36: 0.14613281 | E36: 0.082518433 | F36: 659

Sheet Forecast
A1: Annual forecast and actual-day cash-flow timing
A4: Period | B4: Previous fiscal end | C4: Fiscal end / dates | D4: Cash-flow start | E4: operating_fractions | F4: interest_year_fractions | G4: Selected revenue growth | H4: Selected GP margin | I4: Selected opex margin | J4: Annual capex | K4: WC ratio | L4: revenue | M4: gross_profit | N4: opex | O4: ebitda | P4: ebitda_margin | Q4: working_capital | R4: change_working_capital | S4: cash_capex | T4: cash_ebitda
A5: 1 | B5: =Inputs!$B$6 -> 44531 | C5: =EDATE(B5,12) -> 44896 | D5: =MAX(B5,Inputs!$B$7) -> 44593 | E5: =(C5-D5)/(C5-B5) -> 0.83013699 | F5: =(C5-D5)/365 -> 0.83013699 | G5: =INDEX(Scenarios!$C$5:$C$36,(Inputs!$B$5-1)*8+A5) -> -0.077887208 | H5: =INDEX(Scenarios!$D$5:$D$36,(Inputs!$B$5-1)*8+A5) -> 0.13708598 | I5: =INDEX(Scenarios!$E$5:$E$36,(Inputs!$B$5-1)*8+A5) -> 0.049910311 | J5: =INDEX(Scenarios!$F$5:$F$36,(Inputs!$B$5-1)*8+A5) -> 48 | K5: =Inputs!B31 -> 0.065928097 | L5: =Inputs!$B$9*(1+G5) -> 158324 | M5: =L5*H5 -> 21704 | N5: =L5*I5 -> 7902 | O5: =M5-N5 -> 13802 | P5: =H5-I5 -> 0.087175665 | Q5: =L5*K5 -> 10438 | R5: =Q5-Inputs!$B$10 -> 3785 | S5: =J5*E5 -> 39.846575 | T5: =O5*E5 -> 11457.551
A6: 2 | B6: =C5 -> 44896 | C6: =EDATE(B6,12) -> 45261 | D6: =MAX(B6,Inputs!$B$7) -> 44896 | E6: =(C6-D6)/(C6-B6) -> 1 | F6: =(C6-D6)/365 -> 1 | G6: =INDEX(Scenarios!$C$5:$C$36,(Inputs!$B$5-1)*8+A6) -> 0.22105303 | H6: =INDEX(Scenarios!$D$5:$D$36,(Inputs!$B$5-1)*8+A6) -> 0.14846732 | I6: =INDEX(Scenarios!$E$5:$E$36,(Inputs!$B$5-1)*8+A6) -> 0.048809758 | J6: =INDEX(Scenarios!$F$5:$F$36,(Inputs!$B$5-1)*8+A6) -> 194 | K6: =Inputs!B32 -> 0.066246987 | L6: =L5*(1+G6) -> 193322 | M6: =L6*H6 -> 28702 | N6: =L6*I6 -> 9436 | O6: =M6-N6 -> 19266 | P6: =H6-I6 -> 0.099657566 | Q6: =L6*K6 -> 12807 | R6: =Q6-Q5 -> 2369 | S6: =J6*E6 -> 194 | T6: =O6*E6 -> 19266
A7: 3 | B7: =C6 -> 45261 | C7: =EDATE(B7,12) -> 45627 | D7: =MAX(B7,Inputs!$B$7) -> 45261 | E7: =(C7-D7)/(C7-B7) -> 1 | F7: =(C7-D7)/365 -> 1.0027397 | G7: =INDEX(Scenarios!$C$5:$C$36,(Inputs!$B$5-1)*8+A7) -> 0.20650521 | H7: =INDEX(Scenarios!$D$5:$D$36,(Inputs!$B$5-1)*8+A7) -> 0.15822486 | I7: =INDEX(Scenarios!$E$5:$E$36,(Inputs!$B$5-1)*8+A7) -> 0.048292775 | J7: =INDEX(Scenarios!$F$5:$F$36,(Inputs!$B$5-1)*8+A7) -> 234 | K7: =Inputs!B33 -> 0.063049853 | L7: =L6*(1+G7) -> 233244 | M7: =L7*H7 -> 36905 | N7: =L7*I7 -> 11264 | O7: =M7-N7 -> 25641 | P7: =H7-I7 -> 0.10993209 | Q7: =L7*K7 -> 14706 | R7: =Q7-Q6 -> 1899 | S7: =J7*E7 -> 234 | T7: =O7*E7 -> 25641
A8: 4 | B8: =C7 -> 45627 | C8: =EDATE(B8,12) -> 45992 | D8: =MAX(B8,Inputs!$B$7) -> 45627 | E8: =(C8-D8)/(C8-B8) -> 1 | F8: =(C8-D8)/365 -> 1 | G8: =INDEX(Scenarios!$C$5:$C$36,(Inputs!$B$5-1)*8+A8) -> 0.18377322 | H8: =INDEX(Scenarios!$D$5:$D$36,(Inputs!$B$5-1)*8+A8) -> 0.16634433 | I8: =INDEX(Scenarios!$E$5:$E$36,(Inputs!$B$5-1)*8+A8) -> 0.047778406 | J8: =INDEX(Scenarios!$F$5:$F$36,(Inputs!$B$5-1)*8+A8) -> 345 | K8: =Inputs!B34 -> 0.060610341 | L8: =L7*(1+G8) -> 276108 | M8: =L8*H8 -> 45929 | N8: =L8*I8 -> 13192 | O8: =M8-N8 -> 32737 | P8: =H8-I8 -> 0.11856592 | Q8: =L8*K8 -> 16735 | R8: =Q8-Q7 -> 2029 | S8: =J8*E8 -> 345 | T8: =O8*E8 -> 32737
A9: 5 | B9: =C8 -> 45992 | C9: =EDATE(B9,12) -> 46357 | D9: =MAX(B9,Inputs!$B$7) -> 45992 | E9: =(C9-D9)/(C9-B9) -> 1 | F9: =(C9-D9)/365 -> 1 | G9: =INDEX(Scenarios!$C$5:$C$36,(Inputs!$B$5-1)*8+A9) -> 0.15874585 | H9: =INDEX(Scenarios!$D$5:$D$36,(Inputs!$B$5-1)*8+A9) -> 0.17213281 | I9: =INDEX(Scenarios!$E$5:$E$36,(Inputs!$B$5-1)*8+A9) -> 0.047518433 | J9: =INDEX(Scenarios!$F$5:$F$36,(Inputs!$B$5-1)*8+A9) -> 400 | K9: =Inputs!B35 -> 0.059048756 | L9: =L8*(1+G9) -> 319939 | M9: =L9*H9 -> 55072 | N9: =L9*I9 -> 15203 | O9: =M9-N9 -> 39869 | P9: =H9-I9 -> 0.12461438 | Q9: =L9*K9 -> 18892 | R9: =Q9-Q8 -> 2157 | S9: =J9*E9 -> 400 | T9: =O9*E9 -> 39869
A10: 6 | B10: =C9 -> 46357 | C10: =EDATE(B10,12) -> 46722 | D10: =MAX(B10,Inputs!$B$7) -> 46357 | E10: =(C10-D10)/(C10-B10) -> 1 | F10: =(C10-D10)/365 -> 1 | G10: =INDEX(Scenarios!$C$5:$C$36,(Inputs!$B$5-1)*8+A10) -> 0.13 | H10: =INDEX(Scenarios!$D$5:$D$36,(Inputs!$B$5-1)*8+A10) -> 0.17513281 | I10: =INDEX(Scenarios!$E$5:$E$36,(Inputs!$B$5-1)*8+A10) -> 0.047518433 | J10: =INDEX(Scenarios!$F$5:$F$36,(Inputs!$B$5-1)*8+A10) -> 443 | K10: =Inputs!B36 -> 0.059048756 | L10: =L9*(1+G10) -> 361531.07 | M10: =L10*H10 -> 63315.953 | N10: =L10*I10 -> 17179.39 | O10: =M10-N10 -> 46136.563 | P10: =H10-I10 -> 0.12761438 | Q10: =L10*K10 -> 21347.96 | R10: =Q10-Q9 -> 2455.96 | S10: =J10*E10 -> 443 | T10: =O10*E10 -> 46136.563
A11: 7 | B11: =C10 -> 46722 | C11: =EDATE(B11,12) -> 47088 | D11: =MAX(B11,Inputs!$B$7) -> 46722 | E11: =(C11-D11)/(C11-B11) -> 1 | F11: =(C11-D11)/365 -> 1.0027397 | G11: =INDEX(Scenarios!$C$5:$C$36,(Inputs!$B$5-1)*8+A11) -> 0.12 | H11: =INDEX(Scenarios!$D$5:$D$36,(Inputs!$B$5-1)*8+A11) -> 0.17813281 | I11: =INDEX(Scenarios!$E$5:$E$36,(Inputs!$B$5-1)*8+A11) -> 0.047518433 | J11: =INDEX(Scenarios!$F$5:$F$36,(Inputs!$B$5-1)*8+A11) -> 486 | K11: =Inputs!B37 -> 0.059048756 | L11: =L10*(1+G11) -> 404914.8 | M11: =L11*H11 -> 72128.612 | N11: =L11*I11 -> 19240.917 | O11: =M11-N11 -> 52887.695 | P11: =H11-I11 -> 0.13061438 | Q11: =L11*K11 -> 23909.715 | R11: =Q11-Q10 -> 2561.7552 | S11: =J11*E11 -> 486 | T11: =O11*E11 -> 52887.695
A12: 8 | B12: =C11 -> 47088 | C12: =EDATE(B12,12) -> 47453 | D12: =MAX(B12,Inputs!$B$7) -> 47088 | E12: =(C12-D12)/(C12-B12) -> 1 | F12: =(C12-D12)/365 -> 1 | G12: =INDEX(Scenarios!$C$5:$C$36,(Inputs!$B$5-1)*8+A12) -> 0.11 | H12: =INDEX(Scenarios!$D$5:$D$36,(Inputs!$B$5-1)*8+A12) -> 0.18113281 | I12: =INDEX(Scenarios!$E$5:$E$36,(Inputs!$B$5-1)*8+A12) -> 0.047518433 | J12: =INDEX(Scenarios!$F$5:$F$36,(Inputs!$B$5-1)*8+A12) -> 529 | K12: =Inputs!B38 -> 0.059048756 | L12: =L11*(1+G12) -> 449455.43 | M12: =L12*H12 -> 81411.126 | N12: =L12*I12 -> 21357.418 | O12: =M12-N12 -> 60053.708 | P12: =H12-I12 -> 0.13361438 | Q12: =L12*K12 -> 26539.784 | R12: =Q12-Q11 -> 2630.0687 | S12: =J12*E12 -> 529 | T12: =O12*E12 -> 60053.708

Sheet Debt
A1: Sequential debt, cash and liquidity waterfall
A2: Candidate obligations are diagnostic only on a failed row; executed flows and balances are blank.
A4: Period | B4: Evaluate row? | C4: Opening TLB | D4: Opening RCF | E4: Opening cash | F4: tlb_interest | G4: rcf_interest | H4: cash_interest | I4: tlb_pik | J4: cash_taxes | K4: pre_financing_cash_flow | L4: Proposed mandatory TLB repayment | M4: Proposed mandatory RCF repayment | N4: Cash before repayments | O4: Required draw | P4: Available draw | Q4: Potential funding shortfall | R4: Row status | S4: rcf_draw | T4: Cash after mandatory repayments | U4: Interim RCF | V4: Voluntary RCF repayment | W4: rcf_repayment (total) | X4: Cash after RCF repayment | Y4: tlb_sweep | Z4: tlb_balance | AA4: rcf_balance | AB4: cash_balance
A5: 1 | B5: =AND(A5<=Inputs!$B$8,TRUE()) -> 1 | C5: =IF(B5,Inputs!$B$18,"") -> 60000 | D5: =IF(B5,0,"") -> 0 | E5: =IF(B5,0,"") -> 0 | F5: =IF(B5,C5*Inputs!$B$19*Forecast!F5,"") -> 2988.4932 | G5: =IF(B5,D5*Inputs!$B$25*Forecast!F5,"") -> 0 | H5: =IF(B5,F5+G5,"") -> 2988.4932 | I5: =IF(B5,C5*Inputs!$B$20*Forecast!F5,"") -> 0 | J5: =IF(B5,MAX(Forecast!T5-H5,0)*Inputs!$B$14,"") -> 2117.2644 | K5: =IF(B5,Forecast!T5-Forecast!S5-Forecast!R5-J5,"") -> 5515.4397 | L5: =IF(B5,IF(A5>=Inputs!$B$23,C5+I5,MIN(C5+I5,Inputs!$B$18*Inputs!$B$21*Forecast!E5)),"") -> 0 | M5: =IF(B5,IF(A5>=Inputs!$B$26,D5,0),"") -> 0 | N5: =IF(B5,E5+K5-H5,"") -> 2526.9466 | O5: =IF(B5,MAX(L5+M5-N5,0),"") -> 0 | P5: =IF(B5,IF(A5<Inputs!$B$26,MAX(Inputs!$B$24-D5,0),0),"") -> 15000 | Q5: =IF(B5,MAX(O5-P5,0),"") -> 0 | R5: =IF(B5,IF(Q5>0.00000001,"liquidity_shortfall","ok"),"not_projected") -> ok | S5: =IF(R5="ok",MIN(O5,P5),"") -> 0 | T5: =IF(R5="ok",MAX(N5+S5-L5-M5,0),"") -> 2526.9466 | U5: =IF(R5="ok",D5+S5-M5,"") -> 0 | V5: =IF(R5="ok",MIN(T5,U5),"") -> 0 | W5: =IF(R5="ok",M5+V5,"") -> 0 | X5: =IF(R5="ok",T5-V5,"") -> 2526.9466 | Y5: =IF(R5="ok",MIN(X5*Inputs!$B$22,C5+I5-L5),"") -> 0 | Z5: =IF(R5="ok",C5+I5-L5-Y5,"") -> 60000 | AA5: =IF(R5="ok",U5-V5,"") -> 0 | AB5: =IF(R5="ok",X5-Y5,"") -> 2526.9466
A6: 2 | B6: =AND(A6<=Inputs!$B$8,R5="ok") -> 1 | C6: =IF(B6,Z5,"") -> 60000 | D6: =IF(B6,AA5,"") -> 0 | E6: =IF(B6,AB5,"") -> 2526.9466 | F6: =IF(B6,C6*Inputs!$B$19*Forecast!F6,"") -> 3600 | G6: =IF(B6,D6*Inputs!$B$25*Forecast!F6,"") -> 0 | H6: =IF(B6,F6+G6,"") -> 3600 | I6: =IF(B6,C6*Inputs!$B$20*Forecast!F6,"") -> 0 | J6: =IF(B6,MAX(Forecast!T6-H6,0)*Inputs!$B$14,"") -> 3916.5 | K6: =IF(B6,Forecast!T6-Forecast!S6-Forecast!R6-J6,"") -> 12786.5 | L6: =IF(B6,IF(A6>=Inputs!$B$23,C6+I6,MIN(C6+I6,Inputs!$B$18*Inputs!$B$21*Forecast!E6)),"") -> 0 | M6: =IF(B6,IF(A6>=Inputs!$B$26,D6,0),"") -> 0 | N6: =IF(B6,E6+K6-H6,"") -> 11713.447 | O6: =IF(B6,MAX(L6+M6-N6,0),"") -> 0 | P6: =IF(B6,IF(A6<Inputs!$B$26,MAX(Inputs!$B$24-D6,0),0),"") -> 15000 | Q6: =IF(B6,MAX(O6-P6,0),"") -> 0 | R6: =IF(B6,IF(Q6>0.00000001,"liquidity_shortfall","ok"),"not_projected") -> ok | S6: =IF(R6="ok",MIN(O6,P6),"") -> 0 | T6: =IF(R6="ok",MAX(N6+S6-L6-M6,0),"") -> 11713.447 | U6: =IF(R6="ok",D6+S6-M6,"") -> 0 | V6: =IF(R6="ok",MIN(T6,U6),"") -> 0 | W6: =IF(R6="ok",M6+V6,"") -> 0 | X6: =IF(R6="ok",T6-V6,"") -> 11713.447 | Y6: =IF(R6="ok",MIN(X6*Inputs!$B$22,C6+I6-L6),"") -> 0 | Z6: =IF(R6="ok",C6+I6-L6-Y6,"") -> 60000 | AA6: =IF(R6="ok",U6-V6,"") -> 0 | AB6: =IF(R6="ok",X6-Y6,"") -> 11713.447
A7: 3 | B7: =AND(A7<=Inputs!$B$8,R6="ok") -> 1 | C7: =IF(B7,Z6,"") -> 60000 | D7: =IF(B7,AA6,"") -> 0 | E7: =IF(B7,AB6,"") -> 11713.447 | F7: =IF(B7,C7*Inputs!$B$19*Forecast!F7,"") -> 3609.863 | G7: =IF(B7,D7*Inputs!$B$25*Forecast!F7,"") -> 0 | H7: =IF(B7,F7+G7,"") -> 3609.863 | I7: =IF(B7,C7*Inputs!$B$20*Forecast!F7,"") -> 0 | J7: =IF(B7,MAX(Forecast!T7-H7,0)*Inputs!$B$14,"") -> 5507.7842 | K7: =IF(B7,Forecast!T7-Forecast!S7-Forecast!R7-J7,"") -> 18000.216 | L7: =IF(B7,IF(A7>=Inputs!$B$23,C7+I7,MIN(C7+I7,Inputs!$B$18*Inputs!$B$21*Forecast!E7)),"") -> 0 | M7: =IF(B7,IF(A7>=Inputs!$B$26,D7,0),"") -> 0 | N7: =IF(B7,E7+K7-H7,"") -> 26103.799 | O7: =IF(B7,MAX(L7+M7-N7,0),"") -> 0 | P7: =IF(B7,IF(A7<Inputs!$B$26,MAX(Inputs!$B$24-D7,0),0),"") -> 15000 | Q7: =IF(B7,MAX(O7-P7,0),"") -> 0 | R7: =IF(B7,IF(Q7>0.00000001,"liquidity_shortfall","ok"),"not_projected") -> ok | S7: =IF(R7="ok",MIN(O7,P7),"") -> 0 | T7: =IF(R7="ok",MAX(N7+S7-L7-M7,0),"") -> 26103.799 | U7: =IF(R7="ok",D7+S7-M7,"") -> 0 | V7: =IF(R7="ok",MIN(T7,U7),"") -> 0 | W7: =IF(R7="ok",M7+V7,"") -> 0 | X7: =IF(R7="ok",T7-V7,"") -> 26103.799 | Y7: =IF(R7="ok",MIN(X7*Inputs!$B$22,C7+I7-L7),"") -> 0 | Z7: =IF(R7="ok",C7+I7-L7-Y7,"") -> 60000 | AA7: =IF(R7="ok",U7-V7,"") -> 0 | AB7: =IF(R7="ok",X7-Y7,"") -> 26103.799
A8: 4 | B8: =AND(A8<=Inputs!$B$8,R7="ok") -> 1 | C8: =IF(B8,Z7,"") -> 60000 | D8: =IF(B8,AA7,"") -> 0 | E8: =IF(B8,AB7,"") -> 26103.799 | F8: =IF(B8,C8*Inputs!$B$19*Forecast!F8,"") -> 3600 | G8: =IF(B8,D8*Inputs!$B$25*Forecast!F8,"") -> 0 | H8: =IF(B8,F8+G8,"") -> 3600 | I8: =IF(B8,C8*Inputs!$B$20*Forecast!F8,"") -> 0 | J8: =IF(B8,MAX(Forecast!T8-H8,0)*Inputs!$B$14,"") -> 7284.25 | K8: =IF(B8,Forecast!T8-Forecast!S8-Forecast!R8-J8,"") -> 23078.75 | L8: =IF(B8,IF(A8>=Inputs!$B$23,C8+I8,MIN(C8+I8,Inputs!$B$18*Inputs!$B$21*Forecast!E8)),"") -> 0 | M8: =IF(B8,IF(A8>=Inputs!$B$26,D8,0),"") -> 0 | N8: =IF(B8,E8+K8-H8,"") -> 45582.549 | O8: =IF(B8,MAX(L8+M8-N8,0),"") -> 0 | P8: =IF(B8,IF(A8<Inputs!$B$26,MAX(Inputs!$B$24-D8,0),0),"") -> 15000 | Q8: =IF(B8,MAX(O8-P8,0),"") -> 0 | R8: =IF(B8,IF(Q8>0.00000001,"liquidity_shortfall","ok"),"not_projected") -> ok | S8: =IF(R8="ok",MIN(O8,P8),"") -> 0 | T8: =IF(R8="ok",MAX(N8+S8-L8-M8,0),"") -> 45582.549 | U8: =IF(R8="ok",D8+S8-M8,"") -> 0 | V8: =IF(R8="ok",MIN(T8,U8),"") -> 0 | W8: =IF(R8="ok",M8+V8,"") -> 0 | X8: =IF(R8="ok",T8-V8,"") -> 45582.549 | Y8: =IF(R8="ok",MIN(X8*Inputs!$B$22,C8+I8-L8),"") -> 0 | Z8: =IF(R8="ok",C8+I8-L8-Y8,"") -> 60000 | AA8: =IF(R8="ok",U8-V8,"") -> 0 | AB8: =IF(R8="ok",X8-Y8,"") -> 45582.549
A9: 5 | B9: =AND(A9<=Inputs!$B$8,R8="ok") -> 1 | C9: =IF(B9,Z8,"") -> 60000 | D9: =IF(B9,AA8,"") -> 0 | E9: =IF(B9,AB8,"") -> 45582.549 | F9: =IF(B9,C9*Inputs!$B$19*Forecast!F9,"") -> 3600 | G9: =IF(B9,D9*Inputs!$B$25*Forecast!F9,"") -> 0 | H9: =IF(B9,F9+G9,"") -> 3600 | I9: =IF(B9,C9*Inputs!$B$20*Forecast!F9,"") -> 0 | J9: =IF(B9,MAX(Forecast!T9-H9,0)*Inputs!$B$14,"") -> 9067.25 | K9: =IF(B9,Forecast!T9-Forecast!S9-Forecast!R9-J9,"") -> 28244.75 | L9: =IF(B9,IF(A9>=Inputs!$B$23,C9+I9,MIN(C9+I9,Inputs!$B$18*Inputs!$B$21*Forecast!E9)),"") -> 0 | M9: =IF(B9,IF(A9>=Inputs!$B$26,D9,0),"") -> 0 | N9: =IF(B9,E9+K9-H9,"") -> 70227.299 | O9: =IF(B9,MAX(L9+M9-N9,0),"") -> 0 | P9: =IF(B9,IF(A9<Inputs!$B$26,MAX(Inputs!$B$24-D9,0),0),"") -> 15000 | Q9: =IF(B9,MAX(O9-P9,0),"") -> 0 | R9: =IF(B9,IF(Q9>0.00000001,"liquidity_shortfall","ok"),"not_projected") -> ok | S9: =IF(R9="ok",MIN(O9,P9),"") -> 0 | T9: =IF(R9="ok",MAX(N9+S9-L9-M9,0),"") -> 70227.299 | U9: =IF(R9="ok",D9+S9-M9,"") -> 0 | V9: =IF(R9="ok",MIN(T9,U9),"") -> 0 | W9: =IF(R9="ok",M9+V9,"") -> 0 | X9: =IF(R9="ok",T9-V9,"") -> 70227.299 | Y9: =IF(R9="ok",MIN(X9*Inputs!$B$22,C9+I9-L9),"") -> 0 | Z9: =IF(R9="ok",C9+I9-L9-Y9,"") -> 60000 | AA9: =IF(R9="ok",U9-V9,"") -> 0 | AB9: =IF(R9="ok",X9-Y9,"") -> 70227.299
A10: 6 | B10: =AND(A10<=Inputs!$B$8,R9="ok") -> 0 | C10: =IF(B10,Z9,"") | D10: =IF(B10,AA9,"") | E10: =IF(B10,AB9,"") | F10: =IF(B10,C10*Inputs!$B$19*Forecast!F10,"") | G10: =IF(B10,D10*Inputs!$B$25*Forecast!F10,"") | H10: =IF(B10,F10+G10,"") | I10: =IF(B10,C10*Inputs!$B$20*Forecast!F10,"") | J10: =IF(B10,MAX(Forecast!T10-H10,0)*Inputs!$B$14,"") | K10: =IF(B10,Forecast!T10-Forecast!S10-Forecast!R10-J10,"") | L10: =IF(B10,IF(A10>=Inputs!$B$23,C10+I10,MIN(C10+I10,Inputs!$B$18*Inputs!$B$21*Forecast!E10)),"") | M10: =IF(B10,IF(A10>=Inputs!$B$26,D10,0),"") | N10: =IF(B10,E10+K10-H10,"") | O10: =IF(B10,MAX(L10+M10-N10,0),"") | P10: =IF(B10,IF(A10<Inputs!$B$26,MAX(Inputs!$B$24-D10,0),0),"") | Q10: =IF(B10,MAX(O10-P10,0),"") | R10: =IF(B10,IF(Q10>0.00000001,"liquidity_shortfall","ok"),"not_projected") -> not_projected | S10: =IF(R10="ok",MIN(O10,P10),"") | T10: =IF(R10="ok",MAX(N10+S10-L10-M10,0),"") | U10: =IF(R10="ok",D10+S10-M10,"") | V10: =IF(R10="ok",MIN(T10,U10),"") | W10: =IF(R10="ok",M10+V10,"") | X10: =IF(R10="ok",T10-V10,"") | Y10: =IF(R10="ok",MIN(X10*Inputs!$B$22,C10+I10-L10),"") | Z10: =IF(R10="ok",C10+I10-L10-Y10,"") | AA10: =IF(R10="ok",U10-V10,"") | AB10: =IF(R10="ok",X10-Y10,"")
A11: 7 | B11: =AND(A11<=Inputs!$B$8,R10="ok") -> 0 | C11: =IF(B11,Z10,"") | D11: =IF(B11,AA10,"") | E11: =IF(B11,AB10,"") | F11: =IF(B11,C11*Inputs!$B$19*Forecast!F11,"") | G11: =IF(B11,D11*Inputs!$B$25*Forecast!F11,"") | H11: =IF(B11,F11+G11,"") | I11: =IF(B11,C11*Inputs!$B$20*Forecast!F11,"") | J11: =IF(B11,MAX(Forecast!T11-H11,0)*Inputs!$B$14,"") | K11: =IF(B11,Forecast!T11-Forecast!S11-Forecast!R11-J11,"") | L11: =IF(B11,IF(A11>=Inputs!$B$23,C11+I11,MIN(C11+I11,Inputs!$B$18*Inputs!$B$21*Forecast!E11)),"") | M11: =IF(B11,IF(A11>=Inputs!$B$26,D11,0),"") | N11: =IF(B11,E11+K11-H11,"") | O11: =IF(B11,MAX(L11+M11-N11,0),"") | P11: =IF(B11,IF(A11<Inputs!$B$26,MAX(Inputs!$B$24-D11,0),0),"") | Q11: =IF(B11,MAX(O11-P11,0),"") | R11: =IF(B11,IF(Q11>0.00000001,"liquidity_shortfall","ok"),"not_projected") -> not_projected | S11: =IF(R11="ok",MIN(O11,P11),"") | T11: =IF(R11="ok",MAX(N11+S11-L11-M11,0),"") | U11: =IF(R11="ok",D11+S11-M11,"") | V11: =IF(R11="ok",MIN(T11,U11),"") | W11: =IF(R11="ok",M11+V11,"") | X11: =IF(R11="ok",T11-V11,"") | Y11: =IF(R11="ok",MIN(X11*Inputs!$B$22,C11+I11-L11),"") | Z11: =IF(R11="ok",C11+I11-L11-Y11,"") | AA11: =IF(R11="ok",U11-V11,"") | AB11: =IF(R11="ok",X11-Y11,"")
A12: 8 | B12: =AND(A12<=Inputs!$B$8,R11="ok") -> 0 | C12: =IF(B12,Z11,"") | D12: =IF(B12,AA11,"") | E12: =IF(B12,AB11,"") | F12: =IF(B12,C12*Inputs!$B$19*Forecast!F12,"") | G12: =IF(B12,D12*Inputs!$B$25*Forecast!F12,"") | H12: =IF(B12,F12+G12,"") | I12: =IF(B12,C12*Inputs!$B$20*Forecast!F12,"") | J12: =IF(B12,MAX(Forecast!T12-H12,0)*Inputs!$B$14,"") | K12: =IF(B12,Forecast!T12-Forecast!S12-Forecast!R12-J12,"") | L12: =IF(B12,IF(A12>=Inputs!$B$23,C12+I12,MIN(C12+I12,Inputs!$B$18*Inputs!$B$21*Forecast!E12)),"") | M12: =IF(B12,IF(A12>=Inputs!$B$26,D12,0),"") | N12: =IF(B12,E12+K12-H12,"") | O12: =IF(B12,MAX(L12+M12-N12,0),"") | P12: =IF(B12,IF(A12<Inputs!$B$26,MAX(Inputs!$B$24-D12,0),0),"") | Q12: =IF(B12,MAX(O12-P12,0),"") | R12: =IF(B12,IF(Q12>0.00000001,"liquidity_shortfall","ok"),"not_projected") -> not_projected | S12: =IF(R12="ok",MIN(O12,P12),"") | T12: =IF(R12="ok",MAX(N12+S12-L12-M12,0),"") | U12: =IF(R12="ok",D12+S12-M12,"") | V12: =IF(R12="ok",MIN(T12,U12),"") | W12: =IF(R12="ok",M12+V12,"") | X12: =IF(R12="ok",T12-V12,"") | Y12: =IF(R12="ok",MIN(X12*Inputs!$B$22,C12+I12-L12),"") | Z12: =IF(R12="ok",C12+I12-L12-Y12,"") | AA12: =IF(R12="ok",U12-V12,"") | AB12: =IF(R12="ok",X12-Y12,"")

Sheet Returns
A1: Entry funding, exit priority waterfall and native XIRR
A4: Output | B4: Value
A5: entry_ebitda | B5: =Forecast!O5 -> 13802
A6: entry_ev | B6: =B5*Inputs!$B$11 -> 110416
A7: entry_equity | B7: =B6-Inputs!$B$18 -> 50416
A8: ordinary_equity | B8: =B7*Inputs!$B$15 -> 5041.6
A9: preferred_equity | B9: =B7-B8 -> 45374.4
A10: sponsor_investment | B10: =B7-B11 -> 49911.84
A11: management_investment | B11: =B8*Inputs!$B$16 -> 504.16
A13: exit_date | B13: =INDEX(Forecast!C5:C12,Inputs!$B$8) -> 46357
A14: holding_period_years | B14: =(B13-Inputs!$B$7)/365 -> 4.8328767
A16: status | B16: =IF(COUNTIF(Debt!R5:R12,"liquidity_shortfall")>0,"liquidity_shortfall","ok") -> ok
A17: failure_period | B17: =IF(B16="ok","",MATCH("liquidity_shortfall",Debt!R5:R12,0))
A18: funding_shortfall | B18: =IF(B16="ok",0,INDEX(Debt!Q5:Q12,B17)) -> 0
A20: exit_ev | B20: =IF($B$16="ok",INDEX(Forecast!O5:O12,Inputs!$B$8)*Inputs!$B$12,"") -> 318952
A21: exit_fees | B21: =IF($B$16="ok",MAX(B20,0)*Inputs!$B$13,"") -> 9568.56
A22: exit_debt | B22: =IF($B$16="ok",INDEX(Debt!Z5:Z12,Inputs!$B$8)+INDEX(Debt!AA5:AA12,Inputs!$B$8),"") -> 60000
A23: exit_cash | B23: =IF($B$16="ok",INDEX(Debt!AB5:AB12,Inputs!$B$8),"") -> 70227.299
A24: equity_value_before_floor | B24: =IF($B$16="ok",B20-B21-B22+B23,"") -> 319610.74
A25: equity_proceeds | B25: =IF($B$16="ok",MAX(B24,0),"") -> 319610.74
A27: preferred_accrued | B27: =IF($B$16="ok",B9*(1+Inputs!$B$17)^B14,"") -> 65817.864
A28: preferred_payout | B28: =IF($B$16="ok",IF(B25-B27<=0.000000000001*B25,B25,B27),"") -> 65817.864
A29: ordinary_payout | B29: =IF($B$16="ok",B25-B28,"") -> 253792.88
A30: sponsor_proceeds | B30: =IF($B$16="ok",B28+B29*(1-Inputs!$B$16),"") -> 294231.45
A31: management_proceeds | B31: =IF($B$16="ok",B29*Inputs!$B$16,"") -> 25379.288
A33: deal_mom | B33: =IF(AND($B$16="ok",B7>0),B25/B7,"") -> 6.3394704
A34: sponsor_mom | B34: =IF(AND($B$16="ok",B10>0),B30/B10,"") -> 5.8950231
A35: management_mom | B35: =IF(AND($B$16="ok",B11>0),B31/B11,"") -> 50.339748
A37: deal_irr | B37: =IF(AND($B$16="ok",B7>0,B25>0),XIRR(C44:C45,$B$44:$B$45,MAX(-0.999999999999999,EXP(LN(B25/B7)/$B$14)-1)),"") -> 0.46540502
A38: sponsor_irr | B38: =IF(AND($B$16="ok",B10>0,B30>0),XIRR(D44:D45,$B$44:$B$45,MAX(-0.999999999999999,EXP(LN(B30/B10)/$B$14)-1)),"") -> 0.44353014
A39: management_irr | B39: =IF(AND($B$16="ok",B11>0,B31>0),XIRR(E44:E45,$B$44:$B$45,MAX(-0.999999999999999,EXP(LN(B31/B11)/$B$14)-1)),"") -> 1.249846
A43: Cash-flow event | B43: Actual date | C43: Deal | D43: Sponsor | E43: Management
A44: Entry investment | B44: =Inputs!$B$7 -> 44593 | C44: =-B7 -> -50416 | D44: =-B10 -> -49911.84 | E44: =-B11 -> -504.16
A45: Exit distribution | B45: =B13 -> 46357 | C45: =IF($B$16="ok",B25,"") -> 319610.74 | D45: =IF($B$16="ok",B30,"") -> 294231.45 | E45: =IF($B$16="ok",B31,"") -> 25379.288
A48: Blank valuation or return cells map to JSON null, never fabricated zero returns.
A49: Priority: sponsor preferred first, then ordinary split; distributions sum to equity proceeds.
